.gitignore
.isort.cfg
CONTRIBUTING.rst
LICENSE.txt
MANIFEST.in
Makefile
README.rst
pytest.ini
setup.cfg
setup.py
tox.ini
.github/workflows/python-package.yml
.github/workflows/python-publish.yml
django_frontend_settings.egg-info/PKG-INFO
django_frontend_settings.egg-info/SOURCES.txt
django_frontend_settings.egg-info/dependency_links.txt
django_frontend_settings.egg-info/not-zip-safe
django_frontend_settings.egg-info/requires.txt
django_frontend_settings.egg-info/top_level.txt
frontend_settings/__init__.py
frontend_settings/settings.py
frontend_settings/utils.py
frontend_settings/views.py
tests/__init__.py
tests/factories.py
tests/settings.py
tests/test_views.py
tests/urls.py